Workbook

Sheet Module Summary
A1: Module Name | B1: Frontend Status | C1: Backend Status | D1: Overall Status | E1: Completed Features | F1: Pending Work | G1: Bug Count | H1: Priority | I1: Notes
A2: Authentication and login approval | B2: Partially Completed | C2: Partially Completed | D2: Partially Completed | E2: Admin sign-in, staff password, approval queue, verbal code, and optional server-side approval bypass are implemented in screens and accounts APIs. | F2: Alias words in credential check can select the first matching role. Runtime of the current screens was not executed in this audit. | G2: =COUNTIFS(Bugs!B:B,A2,Bugs!H:H,"Confirmed") | H2: Frontend: LoginScreen, OperatorWaitingScreen, VerbalOtpScreen, AdminPinSetupScreen, ApprovalQueueScreen. Backend: accounts/views.py and accounts/urls.py.
A3: Staff and permissions | B3: Partially Completed | C3: Partially Completed | D3: Partially Completed | E3: Admin can maintain staff from StaffManagementScreen through /api/staff/. Staff records are forced to the staff role. | F3: MenuRightsScreen.tsx is not mounted in App.tsx. This audit did not call the staff API. | G3: =COUNTIFS(Bugs!B:B,A3,Bugs!H:H,"Confirmed") | H3: frontend/src/screens/admin/StaffManagementScreen.tsx; backend/accounts/staff_views.py. Menu rights file is unused by App.tsx.
A4: Branches | B4: Partially Completed | C4: Partially Completed | D4: Partially Completed | E4: Entity master lists and edits branches and their brands through the entities API. | F4: Runtime was not executed in this audit. | G4: =COUNTIFS(Bugs!B:B,A4,Bugs!H:H,"Confirmed") | H4: EntityMasterScreen.tsx; backend/entities.
A5: Brands | B5: Partially Completed | C5: Partially Completed | D5: Partially Completed | E5: Brand master and branch-brand links are implemented. | F5: Runtime was not executed in this audit. | G5: =COUNTIFS(Bugs!B:B,A5,Bugs!H:H,"Confirmed") | H5: BrandMasterScreen.tsx; backend/brands; EntityBrand on the entity model.
A6: Categories | B6: Partially Completed | C6: Partially Completed | D6: Partially Completed | E6: Category master uses the categories API. | F6: Runtime was not executed in this audit. | G6: =COUNTIFS(Bugs!B:B,A6,Bugs!H:H,"Confirmed") | H6: CategoryMasterScreen.tsx; backend/categories.
A7: Products | B7: Partially Completed | C7: Partially Completed | D7: Partially Completed | E7: Product catalogue reads products, categories, brands, and the selected branch. | F7: Runtime was not executed in this audit. | G7: =COUNTIFS(Bugs!B:B,A7,Bugs!H:H,"Confirmed") | H7: ProductCatalogueScreen.tsx; backend/products.
A8: Parties | B8: Partially Completed | C8: Partially Completed | D8: Partially Completed | E8: Customer master creates, updates, deactivates, and reactivates parties through the customers API. No separate supplier module was found. | F8: PartyMasterScreen.tsx calls the masters API but is not mounted in App.tsx. | G8: =COUNTIFS(Bugs!B:B,A8,Bugs!H:H,"Confirmed") | H8: CustomerMasterScreen.tsx; backend/customers. Unused file: PartyMasterScreen.tsx.
A9: Excel price lists | B9: Partially Completed | C9: Partially Completed | D9: Partially Completed | E9: Price list screen and Excel preview/commit endpoints exist, including quality-price rows. | F9: Runtime of import was not executed in this audit. | G9: =COUNTIFS(Bugs!B:B,A9,Bugs!H:H,"Confirmed") | H9: PriceListScreen.tsx; PriceListImportModal.tsx; price_lists/views.py import_preview and import_commit.
A10: PDF brand price lists | B10: Pending | C10: Pending | D10: Pending | E10: None. No screen imports a PDF price list. | F10: BrandQualityPrice table and migration exist. No Python import uses pdfplumber and no PDF import action was found. | G10: =COUNTIFS(Bugs!B:B,A10,Bugs!H:H,"Confirmed") | H10: price_lists/models.py BrandQualityPrice; price_lists/migrations/0003_pdf_quality_prices.py; price_lists/views.py has Excel import only.
A11: Purchase orders | B11: Partially Completed | C11: Partially Completed | D11: Partially Completed | E11: Purchase order list, entry, pipeline, and Excel import call the purchase-orders API. | F11: Runtime was not executed in this audit. | G11: =COUNTIFS(Bugs!B:B,A11,Bugs!H:H,"Confirmed") | H11: PurchaseOrderScreen.tsx; PurchaseOrderImportModal.tsx; backend/purchase_orders.
A12: Dispatch | B12: Partially Completed | C12: Partially Completed | D12: Partially Completed | E12: Dispatch list and Excel import call the dispatches API. | F12: Runtime was not executed in this audit. | G12: =COUNTIFS(Bugs!B:B,A12,Bugs!H:H,"Confirmed") | H12: DispatchScreen.tsx; DispatchImportModal.tsx; backend/dispatches.
A13: PO dispatch reconciliation | B13: Pending | C13: Partially Completed | D13: Partially Completed | E13: Backend GET /api/dispatches/reconciliation/ and PoDispatchReconciliationScreen.tsx exist. | F13: App.tsx does not mount the screen, and IconRail does not link to it. | G13: =COUNTIFS(Bugs!B:B,A13,Bugs!H:H,"Confirmed") | H13: PoDispatchReconciliationScreen.tsx; dispatches/views.py reconciliation action; dispatches/reconciliation.py.
... A28: Deployment configuration | B28: Not Verified | C28: Not Verified | D28: Not Verified | E28: Not verified on a host. | F28: Settings default DEBUG to true when DJANGO_DEBUG is unset. The host environment was not inspected. | G28: =COUNTIFS(Bugs!B:B,A28,Bugs!H:H,"Confirmed") | H28: backend/config/settings.py DEBUG, SECRET_KEY, and ALLOWED_HOSTS.

Sheet Pending Work
A1: Module Name | B1: Pending Task | C1: Why It Is Pending | D1: Priority | E1: Dependency | F1: Evidence | G1: Status
A2: PDF brand price lists | B2: Build PDF price-list preview and commit | C2: The quality-price table exists, but no import action or screen reads a PDF. | D2: High | E2: Approved price-list table shape | F2: price_lists/models.py BrandQualityPrice; no pdfplumber use in Python; views.py Excel actions only. | G2: Pending
A3: PO dispatch reconciliation | B3: Mount the reconciliation screen in the application shell | C3: The screen and API exist, but App.tsx never renders the screen. | D3: High | E3: Dispatch and purchase order APIs | F3: App.tsx switch has no PoDispatchReconciliationScreen. dispatches/views.py exposes reconciliation. | G3: Pending
A4: Statutory reports | B4: Replace sample statutory screens with ledger-backed reports | C4: The mounted screens use fixed arrays and export buttons that only show a toast. | D4: Critical | E4: A real accounting ledger, which was not found behind these screens | F4: SalesRegisterScreen.tsx initial state; BalanceSheetScreen.tsx export toast; same pattern in the other four files. | G4: Pending
A5: Vouchers, notes, and returns | B5: Post vouchers through the API or remove the sample screens from navigation | C5: Save actions update local state and show a posted message. They do not import an API client. | D5: Critical | E5: Payments and invoice balances | F5: BankReceiptVoucherScreen.tsx showFlash says the bank book was updated. IconRail includes screens 13-20. | G5: Pending
A6: Sales orders | B6: Implement a routed sales-order workflow or leave the unused screen out of scope | C6: The order-form screen is not mounted and its save path is local. The OrderForm model has no API. | D6: High | E6: Party, product, and invoice design | F6: OrderFormScreen.tsx is absent from App.tsx. transactions/models.py is used by admin and seed data. | G6: Pending
A7: Inventory and stock | B7: Add stock movements or stop treating the item quantity as a stock module | C7: Only MasterItem.stock_quantity exists. No receipt, issue, or adjustment flow was found. | D7: High | E7: Item master | F7: masters/models.py stock_quantity; masters/urls.py items route. | G7: Pending
A8: Backup | B8: Replace the local backup animation with a real database backup | C8: The button prepends a row in component state and flashes a verified-snapshot message. | D8: Critical | E8: Database access and an operator-confirmed backup location | F8: BackupScreen.tsx useState initial backups and setBackups. | G8: Pending
A9: Year-end closing | B9: Implement a server-side year close or remove the screen | C9: Execute only checks a browser PIN and then calls setFinancialYear. | D9: Critical | E9: Ledger close rules, which are not implemented | F9: YearEndClosingScreen.tsx handleExecuteClosing. | G9: Pending
A10: Audit log | B10: Load /api/auth/audit-trail and make export write a file | C10: The visible grid reads ErpContext auditLogs. Export calls notifyInfo only. | D10: High | E10: Authentication audit endpoint | F10: AuditLogScreen.tsx; accounts/urls.py path api/auth/audit-trail. | G10: Pending
A11: Staff and permissions | B11: Decide whether menu rights stay out of the product | C11: MenuRightsScreen.tsx is not imported by App.tsx. Staff maintenance itself is mounted. | D11: Medium | E11: Staff role model | F11: App.tsx screen 7 is StaffManagementScreen. MenuRightsScreen has no other importer. | G11: Pending
A12: Operational reports | B12: Populate bad-debt write-off totals | C12: The report service leaves monthly write-off totals empty until a write-off module exists. | D12: Medium | E12: A write-off module, which was not found | F12: reports/services.py TODO at the bad-debt totals. | G12: Pending
... A17: Deployment configuration | B17: Inspect the host environment without recording secret values | C17: Code defaults were read. The running host was not inspected, so production debug and secret state are unknown. | D17: High | E17: Access to the host environment | F17: config/settings.py. No host process was queried. | G17: Not Verified

Sheet Bugs
A1: Bug ID | B1: Module Name | C1: Bug Description | D1: Steps to Reproduce | E1: Expected Result | F1: Actual Result | G1: Severity | H1: Confirmed or Potential | I1: Evidence | J1: Status
A2: B01 | B2: Year-end closing | C2: Any PIN of four or more characters is accepted, and the screen then reports that the financial year was locked and balances were rolled. | D2: Open Year-End Closing, enter any PIN of at least four characters, and execute closing. | E2: A wrong PIN is rejected, and a close writes the new year on the server. | F2: The length check passes. The handler calls setFinancialYear('2026-27') and shows a success flash. No closing API is called. | G2: Critical | H2: Confirmed | I2: YearEndClosingScreen.tsx handleExecuteClosing: pin !== '1984' && pin.length < 4. | J2: Open
A3: B02 | B3: Backup | C3: Backup reports that a full snapshot was generated and verified against a SHA-256 hash. | D3: Open Backup and start a backup. | E3: A database dump is created and can be restored. | F3: The handler inserts a row into local component state and flashes success. No backup API is called. | G3: High | H3: Confirmed | I3: BackupScreen.tsx setBackups and the verified-snapshot flash. | J3: Open
A4: B03 | B4: Statutory reports | C4: Sales register, purchase register, trial balance, balance sheet, profit and loss, and bank/cash book show fixed sample figures as the books. | D4: Open any of those screens from the application shell. | E4: Figures come from posted invoices, payments, and ledger balances. | F4: Rows are written in the component, including named sample parties and amounts. Export actions only call showFlash. | G4: High | H4: Confirmed | I4: SalesRegisterScreen.tsx useState invoices; PurchaseRegisterScreen.tsx; TrialBalanceScreen.tsx rows; BalanceSheetScreen.tsx; ProfitAndLossScreen.tsx; BankCashBookScreen.tsx. | J4: Open
A5: B04 | B5: Vouchers, notes, and returns | C5: Saving a bank receipt tells the user the bank book was updated, but the screen never calls the payments API. | D5: Open Bank Receipt Voucher and save. The same local pattern is in cash receipt, payment voucher, credit note, debit note, material return, and voucher-menu payment adjustment. | E5: The receipt is stored and allocated against live invoices. | F5: BankReceiptVoucherScreen flashes that the voucher was posted and the bank book updated. The file does not import an API client. The other six screens likewise keep local state. | G5: High | H5: Confirmed | I5: BankReceiptVoucherScreen.tsx showFlash; App.tsx cases 13, 14, 15, 17, 18, 19, 20. | J5: Open
A6: B05 | B6: Sales orders | C6: The order-form screen reports that orders were registered or committed. | D6: The screen is not mounted, so this cannot be clicked from navigation. The handler is visible in source. | E6: An order is stored through an API. | F6: handleSimulateBulkImport and the register handler call showFlash. There is no sales-order API. | G6: Medium | H6: Confirmed | I6: OrderFormScreen.tsx. Not referenced by App.tsx. | J6: Open
A7: B06 | B7: Audit log | C7: Export says it is exporting a signed CSV archive with a SHA256 checksum. | D7: Open Audit Log and press export. | E7: A file is downloaded from the audit endpoint. | F7: The click handler only calls notifyInfo. The grid reads browser context, not /api/auth/audit-trail. | G7: Medium | H7: Confirmed | I7: AuditLogScreen.tsx notifyInfo export label. | J7: Open
A8: B07 | B8: Authentication and login approval | C8: Credential check treats staff, operator, bhavin, bhavin.operator, op-04, and user as the first active staff account when that account's password matches. | D8: POST the credential check with username staff and the password of the first active staff user. | E8: Those words are rejected unless they are the real username. | F8: The view replaces the username with the first staff user before check_password. | G8: High | H8: Confirmed | I8: accounts/views.py check_credentials alias tuple. | J8: Open
A9: B08 | B9: Deployment configuration | C9: If DJANGO_DEBUG is unset, DEBUG is true and ALLOWED_HOSTS becomes all hosts. An empty secret falls back to a dev key only while DEBUG is true. | D9: Not run against a host. | E9: A deployed process has debug off, a private secret, and an explicit host list. | F9: Not observed on a host. This is a code default, not a confirmed live exposure. | G9: High | H9: Potential | I9: config/settings.py lines that read DJANGO_DEBUG and DJANGO_SECRET_KEY. Secret value was not copied. | J9: Not Verified

Sheet Completed Work
A1: Module Name | B1: Completed Feature | C1: Verification Method | D1: Evidence | E1: Notes
A2: Authentication and login approval | B2: Admin login, staff login request, approval, verbal code, and session endpoints | C2: Code inspection. Endpoints were not called in this audit. | D2: accounts/urls.py auth routes; LoginScreen.tsx; VerbalOtpScreen.tsx; ApprovalQueueScreen.tsx through ErpContext. | E2: Not marked Completed because runtime was not executed.
A3: Staff and permissions | B3: Staff list, create, update, and deactivate for admin | C3: Code inspection. API was not called in this audit. | D3: StaffManagementScreen.tsx; accounts/staff_views.py; accounts/urls.py staff router. | E3: Menu rights are not part of this feature.
A4: Branches | B4: Branch master with brand links | C4: Code inspection. | D4: EntityMasterScreen.tsx; entities API router. | E4: Runtime not executed.
A5: Brands | B5: Brand master and branch assignment | C5: Code inspection. | D5: BrandMasterScreen.tsx; brands API router. | E5: Runtime not executed.
A6: Categories | B6: Category master | C6: Code inspection. | D6: CategoryMasterScreen.tsx; categories API router. | E6: Runtime not executed.
A7: Products | B7: Product catalogue filtered by the selected branch | C7: Code inspection of the screen and products API. | D7: ProductCatalogueScreen.tsx; products API router. | E7: Runtime not executed.
A8: Parties | B8: Party create, update, deactivate, reactivate, and permanent remove | C8: Code inspection of CustomerMasterScreen handlers. | D8: CustomerMasterScreen.tsx customersApi calls; customers API router. | E8: No separate supplier master was found.
A9: Excel price lists | B9: Excel price-list preview and commit, including quality rows | C9: Code inspection of the modal and view actions. | D9: PriceListImportModal.tsx; price_lists/views.py import_preview and import_commit. | E9: PDF import is not included.
A10: Purchase orders | B10: Purchase order list, entry, pipeline, and Excel import | C10: Code inspection. | D10: PurchaseOrderScreen.tsx; PurchaseOrderImportModal.tsx; purchase-orders router. | E10: Runtime not executed.
A11: Dispatch | B11: Dispatch list and Excel import | C11: Code inspection. | D11: DispatchScreen.tsx; DispatchImportModal.tsx; dispatches router. | E11: Runtime not executed.
A12: PO dispatch reconciliation | B12: Reconciliation query on the dispatch API | C12: Code inspection of the view and service. | D12: dispatches/views.py reconciliation; dispatches/reconciliation.py. | E12: The screen is not mounted, so the user cannot open it.
... A20: Audit log | B20: Backend audit-trail route | C20: Code inspection of the URL. | D20: accounts/urls.py api/auth/audit-trail. | E20: The mounted screen does not call it.

Sheet Lists
A1: Completed | B1: Critical | C1: Confirmed | D1: Open | E1: Pending
A2: Partially Completed | B2: High | C2: Potential | D2: Fixed | E2: In Progress
A3: Pending | B3: Medium | D3: Not Verified | E3: Blocked
A4: Blocked | B4: Low | E4: Not Verified
A5: Not Verified | E5: Done
